<annotation>
	<folder>images</folder>
	<filename>image_0_9636.jpg</filename>
	<path>D:\Docs\On job study\Deep learning\Ubisoft assignment\Assignment\Assignment\Train\images\image_0_9636.jpg</path>
	<source>
		<database>Unknown</database>
	</source>
	<size>
		<width>1886</width>
		<height>737</height>
		<depth>3</depth>
	</size>
	<segmented>0</segmented>
	<object>
		<name>clip</name>
		<pose>Unspecified</pose>
		<truncated>0</truncated>
		<difficult>0</difficult>
		<bndbox>
			<xmin>795</xmin>
			<ymin>241</ymin>
			<xmax>835</xmax>
			<ymax>269</ymax>
		</bndbox>
	</object>
</annotation>
